{
    "number": 153,
    "name": "Bayleef",
    "types": [
        "Grass"
    ],
    "abilities": {
        "normal": [
            "Overgrow"
        ],
        "hidden": [
            "Leaf Guard"
        ]
    },
    "base_hp": 4,
    "strength": "2/4",
    "dexterity": "2/4",
    "vitality": "2/5",
    "special": "2/4",
    "insight": "2/5",
    "moves": {
        "bronze": [
            "Growl",
            "Poison Powder",
            "Razor Leaf",
            "Reflect",
            "Tackle"
        ],
        "silver": [
            "Body Slam",
            "Leech Seed",
            "Magical Leaf",
            "Natural Gift",
            "Nature Power",
            "Sweet Scent",
            "Synthesis"
        ],
        "gold": [
            "Aromatherapy",
            "Giga Drain",
            "Light Screen",
            "Safeguard",
            "Solar Beam"
        ],
        "platinum": [],
        "diamond": [],
        "tm": [
            "Aromatherapy",
            "Attract",
            "Body Slam",
            "Bullet Seed",
            "Captivate",
            "Charm",
            "Confide",
            "Curse",
            "Cut",
            "Detect",
            "Double Team",
            "Double-Edge",
            "Echoed Voice",
            "Encore",
            "Endure",
            "Energy Ball",
            "Facade",
            "Fake Tears",
            "Flash",
            "Frustration",
            "Fury Cutter",
            "Giga Drain",
            "Grass Knot",
            "Grass Pledge",
            "Grassy Glide",
            "Grassy Terrain",
            "Growl",
            "Headbutt",
            "Helping Hand",
            "Hidden Power",
            "Iron Tail",
            "Knock Off",
            "Leaf Storm",
            "Light Screen",
            "Magical Leaf",
            "Mud-Slap",
            "Natural Gift",
            "Nature Power",
            "Poison Powder",
            "Protect",
            "Razor Leaf",
            "Reflect",
            "Rest",
            "Return",
            "Rock Smash",
            "Round",
            "Safeguard",
            "Secret Power",
            "Seed Bomb",
            "Sleep Talk",
            "Snore",
            "Solar Beam",
            "Solar Blade",
            "Stomping Tantrum",
            "Strength",
            "Substitute",
            "Sunny Day",
            "Swagger",
            "Sweet Scent",
            "Swords Dance",
            "Synthesis",
            "Tackle",
            "Take Down",
            "Tera Blast",
            "Toxic",
            "Trailblaze",
            "Work Up",
            "Agility",
            "Amnesia",
            "Iron Defense",
            "Metronome",
            "Nasty Plot",
            "Splash"
        ],
        "tutor": [
            "Ancient Power",
            "Body Slam",
            "Counter",
            "Double-Edge",
            "Fury Cutter",
            "Grass Pledge",
            "Growl",
            "Mimic",
            "Mud-Slap",
            "Poison Powder",
            "Razor Leaf",
            "Reflect",
            "Seed Bomb",
            "Snore",
            "Substitute",
            "Swords Dance",
            "Synthesis",
            "Tackle"
        ],
        "egg": [
            "Ancient Power",
            "Aromatherapy",
            "Body Slam",
            "Counter",
            "Flail",
            "Grass Whistle",
            "Grassy Terrain",
            "Heal Pulse",
            "Ingrain",
            "Leaf Storm",
            "Leech Seed",
            "Nature Power",
            "Refresh",
            "Swords Dance",
            "Vine Whip",
            "Wring Out"
        ],
        "level1_g3_7": [
            "Growl",
            "Razor Leaf",
            "Reflect",
            "Tackle",
            "Poison Powder"
        ]
    }
}
