{
    "number": 445,
    "name": "Garchomp",
    "types": [
        "Dragon",
        "Ground"
    ],
    "abilities": {
        "normal": [
            "Sand Veil"
        ],
        "hidden": [
            "Rough Skin"
        ]
    },
    "base_hp": 6,
    "strength": "4/8",
    "dexterity": "3/6",
    "vitality": "3/6",
    "special": "2/5",
    "insight": "2/5",
    "moves": {
        "bronze": [
            "Crunch",
            "Dragon Breath",
            "Dragon Rage",
            "Dual Chop",
            "Sand Attack",
            "Sand Tomb",
            "Tackle"
        ],
        "silver": [
            "Bite",
            "Bulldoze",
            "Dragon Claw",
            "Sandstorm",
            "Slash",
            "Take Down"
        ],
        "gold": [
            "Dig",
            "Dragon Rush"
        ],
        "platinum": [],
        "diamond": [],
        "tm": [
            "Aerial Ace",
            "Attract",
            "Body Slam",
            "Breaking Swipe",
            "Brick Break",
            "Brutal Swing",
            "Bulldoze",
            "Captivate",
            "Confide",
            "Crunch",
            "Cut",
            "Dig",
            "Double Team",
            "Double-Edge",
            "Draco Meteor",
            "Dragon Cheer",
            "Dragon Claw",
            "Dragon Pulse",
            "Dragon Tail",
            "Earth Power",
            "Earthquake",
            "Endure",
            "Facade",
            "False Swipe",
            "Fire Blast",
            "Fire Fang",
            "Flamethrower",
            "Fling",
            "Frustration",
            "Giga Impact",
            "Helping Hand",
            "Hidden Power",
            "Hone Claws",
            "Hyper Beam",
            "Incinerate",
            "Iron Head",
            "Iron Tail",
            "Liquidation",
            "Metal Claw",
            "Mud Shot",
            "Natural Gift",
            "Outrage",
            "Poison Jab",
            "Power Gem",
            "Protect",
            "Rain Dance",
            "Rest",
            "Return",
            "Roar",
            "Rock Climb",
            "Rock Slide",
            "Rock Smash",
            "Rock Tomb",
            "Round",
            "Sand Tomb",
            "Sandstorm",
            "Scale Shot",
            "Scary Face",
            "Scorching Sands",
            "Secret Power",
            "Shadow Claw",
            "Sleep Talk",
            "Snore",
            "Spikes",
            "Stealth Rock",
            "Stomping Tantrum",
            "Stone Edge",
            "Strength",
            "Substitute",
            "Sunny Day",
            "Surf",
            "Swagger",
            "Swift",
            "Swords Dance",
            "Take Down",
            "Tera Blast",
            "Thunder Fang",
            "Toxic",
            "Whirlpool",
            "Agility",
            "Amnesia",
            "Curse",
            "Headbutt",
            "Iron Defense",
            "Metronome",
            "Nasty Plot",
            "Splash"
        ],
        "tutor": [
            "Crunch",
            "Draco Meteor",
            "Dragon Rage",
            "Dual Chop",
            "Fire Fang",
            "Sand Attack",
            "Sandstorm",
            "Scale Shot",
            "Scorching Sands",
            "Tackle"
        ],
        "egg": [
            "Body Slam",
            "Double-Edge",
            "Dragon Breath",
            "Iron Head",
            "Iron Tail",
            "Metal Claw",
            "Mud Shot",
            "Outrage",
            "Rock Climb",
            "Sand Tomb",
            "Scary Face",
            "Thrash",
            "Twister"
        ],
        "level1_g3_7": [
            "Dragon Rage",
            "Fire Fang",
            "Sand Attack",
            "Sandstorm",
            "Tackle",
            "Crunch",
            "Dual Chop"
        ]
    }
}
