{
    "number": 74,
    "name": "Geodude",
    "types": [
        "Rock",
        "Ground"
    ],
    "abilities": {
        "normal": [
            "Rock Head",
            "Sturdy"
        ],
        "hidden": [
            "Sand Veil"
        ]
    },
    "base_hp": 3,
    "strength": "2/5",
    "dexterity": "1/2",
    "vitality": "3/6",
    "special": "1/2",
    "insight": "1/3",
    "moves": {
        "bronze": [
            "Defense Curl",
            "Mud Sport",
            "Rock Polish",
            "Rollout",
            "Sandstorm",
            "Tackle"
        ],
        "silver": [
            "Bulldoze",
            "Earthquake",
            "Explosion",
            "Harden",
            "Magnitude",
            "Rock Blast",
            "Rock Throw",
            "Self-Destruct",
            "Selfdestruct",
            "Smack Down",
            "Stealth Rock"
        ],
        "gold": [
            "Double-Edge",
            "Stone Edge"
        ],
        "platinum": [],
        "diamond": [],
        "tm": [
            "Attract",
            "Bide",
            "Body Slam",
            "Brick Break",
            "Bulldoze",
            "Captivate",
            "Confide",
            "Counter",
            "Curse",
            "Defense Curl",
            "Dig",
            "Double Team",
            "Double-Edge",
            "Dynamic Punch",
            "Earth Power",
            "Earthquake",
            "Endure",
            "Explosion",
            "Facade",
            "Fire Blast",
            "Fire Punch",
            "Fissure",
            "Flamethrower",
            "Fling",
            "Focus Punch",
            "Frustration",
            "Gyro Ball",
            "Harden",
            "Headbutt",
            "Hidden Power",
            "High Horsepower",
            "Incinerate",
            "Iron Defense",
            "Mega Punch",
            "Metronome",
            "Mimic",
            "Mud Shot",
            "Mud-Slap",
            "Natural Gift",
            "Nature Power",
            "Power-Up Punch",
            "Protect",
            "Rage",
            "Rest",
            "Return",
            "Rock Blast",
            "Rock Climb",
            "Rock Polish",
            "Rock Slide",
            "Rock Smash",
            "Rock Throw",
            "Rock Tomb",
            "Rollout",
            "Round",
            "Sandstorm",
            "Scary Face",
            "Secret Power",
            "Seismic Toss",
            "Self-Destruct",
            "Selfdestruct",
            "Sleep Talk",
            "Smack Down",
            "Snore",
            "Stealth Rock",
            "Stomping Tantrum",
            "Stone Edge",
            "Strength",
            "Submission",
            "Substitute",
            "Sunny Day",
            "Swagger",
            "Tackle",
            "Take Down",
            "Tera Blast",
            "Thunder Punch",
            "Toxic",
            "Agility",
            "Amnesia",
            "Helping Hand",
            "Nasty Plot",
            "Splash",
            "Swords Dance"
        ],
        "tutor": [
            "Ancient Power",
            "Block",
            "Body Slam",
            "Bulldoze",
            "Counter",
            "Defense Curl",
            "Double-Edge",
            "Earth Power",
            "Explosion",
            "Fire Punch",
            "Flamethrower",
            "Focus Punch",
            "Iron Defense",
            "Mega Punch",
            "Metronome",
            "Mimic",
            "Mud-Slap",
            "Rest",
            "Rock Slide",
            "Rock Smash",
            "Rollout",
            "Seismic Toss",
            "Sleep Talk",
            "Snore",
            "Stealth Rock",
            "Stone Edge",
            "Substitute",
            "Sucker Punch",
            "Superpower",
            "Tackle",
            "Thunder Punch"
        ],
        "egg": [
            "Autotomize",
            "Block",
            "Curse",
            "Dynamic Punch",
            "Endure",
            "Flail",
            "Focus Punch",
            "Hammer Arm",
            "Mega Punch",
            "Rock Climb",
            "Rock Slide",
            "Wide Guard"
        ],
        "level1_g3_7": [
            "Defense Curl",
            "Tackle"
        ]
    }
}
