{
    "number": 858,
    "name": "Hatterene",
    "types": [
        "Psychic",
        "Fairy"
    ],
    "abilities": {
        "normal": [
            "Healer",
            "Anticipation"
        ],
        "hidden": [
            "Magic Bounce"
        ]
    },
    "base_hp": 4,
    "strength": "3/6",
    "dexterity": "1/2",
    "vitality": "3/6",
    "special": "4/8",
    "insight": "3/6",
    "moves": {
        "bronze": [
            "Brutal Swing",
            "Confusion",
            "Disarming Voice",
            "Life Dew",
            "Play Nice",
            "Psycho Cut"
        ],
        "silver": [
            "Aromatherapy",
            "Aromatic Mist",
            "Dazzling Gleam",
            "Heal Pulse",
            "Psybeam"
        ],
        "gold": [
            "Calm Mind",
            "Healing Wish",
            "Magic Powder",
            "Psychic"
        ],
        "platinum": [],
        "diamond": [],
        "tm": [
            "Agility",
            "Attract",
            "Baton Pass",
            "Brutal Swing",
            "Calm Mind",
            "Charm",
            "Dark Pulse",
            "Dazzling Gleam",
            "Disarming Voice",
            "Draining Kiss",
            "Endure",
            "Expanding Force",
            "Facade",
            "Future Sight",
            "Giga Drain",
            "Giga Impact",
            "Gravity",
            "Guard Swap",
            "Helping Hand",
            "Hyper Beam",
            "Imprison",
            "Light Screen",
            "Magic Room",
            "Magical Leaf",
            "Metronome",
            "Misty Explosion",
            "Misty Terrain",
            "Mystical Fire",
            "Pain Split",
            "Play Rough",
            "Power Swap",
            "Power Whip",
            "Protect",
            "Psybeam",
            "Psych Up",
            "Psychic",
            "Psychic Noise",
            "Psychic Terrain",
            "Psycho Cut",
            "Psyshock",
            "Reflect",
            "Rest",
            "Round",
            "Safeguard",
            "Shadow Ball",
            "Shadow Claw",
            "Skill Swap",
            "Sleep Talk",
            "Snore",
            "Stored Power",
            "Substitute",
            "Swift",
            "Swords Dance",
            "Tera Blast",
            "Thunder Wave",
            "Trick",
            "Trick Room",
            "Wonder Room",
            "Amnesia",
            "Confide",
            "Curse",
            "Double Team",
            "Frustration",
            "Headbutt",
            "Hidden Power",
            "Iron Defense",
            "Nasty Plot",
            "Return",
            "Secret Power",
            "Splash",
            "Take Down",
            "Captivate",
            "Double Slap",
            "Embargo",
            "Flash",
            "Heal Block",
            "Heart Stamp",
            "Lucky Chant",
            "Meditate",
            "Miracle Eye",
            "Nightmare",
            "Psywave",
            "Signal Beam",
            "Snatch",
            "Synchronoise",
            "Telekinesis",
            "Wring Out"
        ],
        "tutor": [
            "Expanding Force",
            "Misty Explosion"
        ],
        "egg": [
            "After You",
            "Aromatic Mist",
            "Mystical Fire",
            "Nuzzle",
            "Quash"
        ],
        "level1_g3_7": []
    }
}
