{
    "number": 237,
    "name": "Hitmontop",
    "types": [
        "Fighting"
    ],
    "abilities": {
        "normal": [
            "Intimidate",
            "Technician"
        ],
        "hidden": [
            "Steadfast"
        ]
    },
    "base_hp": 3,
    "strength": "3/6",
    "dexterity": "2/5",
    "vitality": "3/6",
    "special": "1/3",
    "insight": "3/6",
    "moves": {
        "bronze": [
            "Fake Out",
            "Feint",
            "Focus Energy",
            "Gyro Ball",
            "Helping Hand",
            "Pursuit",
            "Quick Attack",
            "Rapid Spin",
            "Rolling Kick",
            "Tackle",
            "Triple Kick"
        ],
        "silver": [
            "Agility",
            "Counter",
            "Detect",
            "Dig",
            "Quick Guard",
            "Revenge",
            "Sucker Punch",
            "Wide Guard"
        ],
        "gold": [
            "Close Combat",
            "Endeavor"
        ],
        "platinum": [],
        "diamond": [],
        "tm": [
            "Aerial Ace",
            "Agility",
            "Attract",
            "Baton Pass",
            "Body Slam",
            "Brick Break",
            "Brutal Swing",
            "Bulk Up",
            "Bulldoze",
            "Captivate",
            "Close Combat",
            "Coaching",
            "Confide",
            "Curse",
            "Detect",
            "Dig",
            "Double Team",
            "Double-Edge",
            "Drill Run",
            "Earthquake",
            "Endeavor",
            "Endure",
            "Facade",
            "Focus Blast",
            "Focus Energy",
            "Frustration",
            "Giga Impact",
            "Gyro Ball",
            "Headbutt",
            "Helping Hand",
            "Hidden Power",
            "Ice Spinner",
            "Low Kick",
            "Low Sweep",
            "Mega Kick",
            "Mega Punch",
            "Mud-Slap",
            "Natural Gift",
            "Protect",
            "Rain Dance",
            "Rest",
            "Retaliate",
            "Return",
            "Revenge",
            "Reversal",
            "Rock Slide",
            "Rock Smash",
            "Round",
            "Sandstorm",
            "Secret Power",
            "Sleep Talk",
            "Snore",
            "Stone Edge",
            "Strength",
            "Substitute",
            "Sunny Day",
            "Swagger",
            "Swift",
            "Take Down",
            "Tera Blast",
            "Thief",
            "Toxic",
            "Triple Axel",
            "Upper Hand",
            "Uproar",
            "Vacuum Wave",
            "Work Up",
            "Amnesia",
            "Iron Defense",
            "Metronome",
            "Nasty Plot",
            "Splash",
            "Swords Dance"
        ],
        "tutor": [
            "Body Slam",
            "Close Combat",
            "Coaching",
            "Counter",
            "Covet",
            "Detect",
            "Double-Edge",
            "Drill Run",
            "Endeavor",
            "Focus Energy",
            "Helping Hand",
            "Laser Focus",
            "Low Kick",
            "Mega Kick",
            "Mimic",
            "Mud-Slap",
            "Pursuit",
            "Quick Attack",
            "Revenge",
            "Rock Slide",
            "Role Play",
            "Rolling Kick",
            "Rollout",
            "Seismic Toss",
            "Sleep Talk",
            "Snore",
            "Substitute",
            "Sucker Punch",
            "Swift",
            "Triple Axel",
            "Twister",
            "Vacuum Wave"
        ],
        "egg": [
            "Bullet Punch",
            "Counter",
            "Endure",
            "Feint",
            "Helping Hand",
            "High Jump Kick",
            "Mach Punch",
            "Mind Reader",
            "Pursuit",
            "Rapid Spin",
            "Vacuum Wave"
        ],
        "level1_g3_7": [
            "Revenge",
            "Rolling Kick",
            "Close Combat",
            "Endeavor",
            "Detect",
            "Focus Energy",
            "Pursuit",
            "Quick Attack"
        ]
    }
}
