{
    "number": 686,
    "name": "Inkay",
    "types": [
        "Dark",
        "Psychic"
    ],
    "abilities": {
        "normal": [
            "Contrary",
            "Suction Cups"
        ],
        "hidden": [
            "Infiltrator"
        ]
    },
    "base_hp": 3,
    "strength": "2/4",
    "dexterity": "1/3",
    "vitality": "2/4",
    "special": "1/3",
    "insight": "1/3",
    "moves": {
        "bronze": [
            "Foul Play",
            "Hypnosis",
            "Payback",
            "Peck",
            "Reflect",
            "Tackle",
            "Wrap"
        ],
        "silver": [
            "Light Screen",
            "Night Slash",
            "Pluck",
            "Psybeam",
            "Psycho Cut",
            "Psywave",
            "Slash",
            "Swagger",
            "Switcheroo",
            "Topsy-Turvy"
        ],
        "gold": [
            "Superpower"
        ],
        "platinum": [],
        "diamond": [],
        "tm": [
            "Aerial Ace",
            "Ally Switch",
            "Attract",
            "Baton Pass",
            "Calm Mind",
            "Confide",
            "Cut",
            "Dark Pulse",
            "Double Team",
            "Embargo",
            "Endure",
            "Expanding Force",
            "Facade",
            "Fake Tears",
            "Flamethrower",
            "Flash",
            "Fling",
            "Foul Play",
            "Frustration",
            "Future Sight",
            "Gravity",
            "Guard Swap",
            "Helping Hand",
            "Hidden Power",
            "Knock Off",
            "Lash Out",
            "Light Screen",
            "Liquidation",
            "Lunge",
            "Nasty Plot",
            "Payback",
            "Protect",
            "Psybeam",
            "Psych Up",
            "Psychic",
            "Psycho Cut",
            "Psyshock",
            "Rain Dance",
            "Reflect",
            "Rest",
            "Retaliate",
            "Return",
            "Rock Slide",
            "Round",
            "Skill Swap",
            "Sleep Talk",
            "Snore",
            "Spite",
            "Stored Power",
            "Substitute",
            "Sunny Day",
            "Superpower",
            "Swagger",
            "Swift",
            "Taunt",
            "Tera Blast",
            "Thief",
            "Thunderbolt",
            "Torment",
            "Toxic",
            "Trick",
            "Trick Room",
            "Agility",
            "Amnesia",
            "Curse",
            "Headbutt",
            "Iron Defense",
            "Metronome",
            "Secret Power",
            "Splash",
            "Swords Dance",
            "Take Down"
        ],
        "tutor": [
            "Ally Switch",
            "Bind",
            "Constrict",
            "Expanding Force",
            "Foul Play",
            "Knock Off",
            "Lash Out",
            "Peck",
            "Role Play",
            "Snatch",
            "Snore",
            "Spite",
            "Superpower",
            "Tackle",
            "Telekinesis"
        ],
        "egg": [
            "Acupressure",
            "Camouflage",
            "Destiny Bond",
            "Disable",
            "Flatter",
            "Guard Swap",
            "Power Split",
            "Simple Beam"
        ],
        "level1_g3_7": [
            "Constrict",
            "Peck",
            "Tackle"
        ]
    }
}
