{
    "number": 165,
    "name": "Ledyba",
    "types": [
        "Bug",
        "Flying"
    ],
    "abilities": {
        "normal": [
            "Swarm",
            "Early Bird"
        ],
        "hidden": [
            "Rattled"
        ]
    },
    "base_hp": 3,
    "strength": "1/2",
    "dexterity": "2/4",
    "vitality": "1/2",
    "special": "1/3",
    "insight": "2/5",
    "moves": {
        "bronze": [
            "Comet Punch",
            "Supersonic",
            "Swift",
            "Tackle"
        ],
        "silver": [
            "Agility",
            "Baton Pass",
            "Bug Buzz",
            "Light Screen",
            "Mach Punch",
            "Reflect",
            "Roost",
            "Safeguard",
            "Silver Wind",
            "Struggle Bug"
        ],
        "gold": [
            "Air Slash",
            "Double-Edge"
        ],
        "platinum": [],
        "diamond": [],
        "tm": [
            "Acrobatics",
            "Aerial Ace",
            "Agility",
            "Air Slash",
            "Attract",
            "Baton Pass",
            "Brick Break",
            "Bug Buzz",
            "Captivate",
            "Confide",
            "Curse",
            "Dig",
            "Double Team",
            "Double-Edge",
            "Drain Punch",
            "Dynamic Punch",
            "Endure",
            "Facade",
            "Flash",
            "Fling",
            "Focus Punch",
            "Frustration",
            "Giga Drain",
            "Headbutt",
            "Hidden Power",
            "Ice Punch",
            "Infestation",
            "Light Screen",
            "Mach Punch",
            "Natural Gift",
            "Power-Up Punch",
            "Protect",
            "Reflect",
            "Rest",
            "Return",
            "Rollout",
            "Roost",
            "Round",
            "Safeguard",
            "Secret Power",
            "Silver Wind",
            "Sleep Talk",
            "Snore",
            "Solar Beam",
            "Struggle Bug",
            "Substitute",
            "Sunny Day",
            "Supersonic",
            "Swagger",
            "Sweet Scent",
            "Swift",
            "Swords Dance",
            "Tackle",
            "Thief",
            "Thunder Punch",
            "Toxic",
            "U-turn",
            "Amnesia",
            "Helping Hand",
            "Iron Defense",
            "Metronome",
            "Nasty Plot",
            "Splash",
            "Take Down",
            "Tera Blast"
        ],
        "tutor": [
            "Air Cutter",
            "Bug Bite",
            "Double-Edge",
            "Drain Punch",
            "Focus Punch",
            "Giga Drain",
            "Ice Punch",
            "Knock Off",
            "Mega Punch",
            "Mimic",
            "Ominous Wind",
            "Rollout",
            "Roost",
            "Sleep Talk",
            "Snore",
            "Substitute",
            "Swift",
            "Swords Dance",
            "Tackle",
            "Tailwind",
            "Thunder Punch",
            "Uproar"
        ],
        "egg": [
            "Bide",
            "Bug Bite",
            "Bug Buzz",
            "Counter",
            "Dizzy Punch",
            "Drain Punch",
            "Encore",
            "Endure",
            "Focus Punch",
            "Knock Off",
            "Light Screen",
            "Psybeam",
            "Screech",
            "Silver Wind",
            "Tailwind"
        ],
        "level1_g3_7": [
            "Tackle"
        ]
    }
}
