{
    "number": 745,
    "name": "Lycanroc (Midday)",
    "types": [
        "Rock"
    ],
    "abilities": {
        "normal": [
            "Keen Eye",
            "Sand Rush"
        ],
        "hidden": [
            "Steadfast"
        ]
    },
    "base_hp": 5,
    "strength": "3/7",
    "dexterity": "3/6",
    "vitality": "2/4",
    "special": "2/4",
    "insight": "2/4",
    "moves": {
        "bronze": [
            "Accelerock",
            "Bite",
            "Leer",
            "Quick Attack",
            "Quick Guard",
            "Sand Attack",
            "Tackle",
            "Double Team"
        ],
        "silver": [
            "Howl",
            "Rock Throw",
            "Odor Sleuth",
            "Rock Tomb",
            "Roar",
            "Stealth Rock"
        ],
        "gold": [
            "Rock Slide",
            "Scary Face",
            "Crunch",
            "Rock Climb",
            "Stone Edge"
        ],
        "platinum": [],
        "diamond": [],
        "tm": [
            "Roar",
            "Toxic",
            "Bulk Up",
            "Hidden Power",
            "Taunt",
            "Protect",
            "Frustration",
            "Return",
            "Brick Break",
            "Double Team",
            "Rock Tomb",
            "Facade",
            "Rest",
            "Attract",
            "Round",
            "Echoed Voice",
            "Rock Polish",
            "Stone Edge",
            "Swords Dance",
            "Rock Slide",
            "Swagger",
            "Sleep Talk",
            "Substitute",
            "Snarl",
            "Confide",
            "Agility",
            "Curse",
            "Endure",
            "Headbutt",
            "Helping Hand",
            "Metronome",
            "Nasty Plot",
            "Secret Power",
            "Snore",
            "Splash",
            "Take Down",
            "Tera Blast",
            "Giga Impact",
            "Scary Face",
            "Sandstorm",
            "Swift",
            "Rock Blast",
            "Assurance",
            "Thunder Fang",
            "Fire Fang",
            "Tail Slap",
            "Stomping Tantrum",
            "Iron Tail",
            "Crunch",
            "Hyper Voice",
            "Iron Defense",
            "Close Combat",
            "Earth Power",
            "Zen Headbutt",
            "Iron Head",
            "Stealth Rock",
            "Drill Run",
            "Play Rough",
            "Psychic Fangs",
            "Charm",
            "Mud-Slap",
            "Trailblaze",
            "Bulldoze",
            "Sunny Day",
            "Dig",
            "Body Slam",
            "Double-Edge",
            "Endeavor",
            "Amnesia"
        ],
        "egg": [
            "Crush Claw",
            "Fire Fang",
            "Sucker Punch",
            "Thrash",
            "Thunder Fang",
            "Endeavor"
        ],
        "tutor": [
            "Covet",
            "Drill Run",
            "Earth Power",
            "Endeavor",
            "Hyper Voice",
            "Iron Defense",
            "Iron Head",
            "Iron Tail",
            "Last Resort",
            "Snore",
            "Stealth Rock",
            "Stomping Tantrum",
            "Zen Headbutt",
            "Lash Out"
        ]
    }
}
