{
    "number": 89,
    "name": "Muk",
    "types": [
        "Poison"
    ],
    "abilities": {
        "normal": [
            "Stench",
            "Sticky Hold"
        ],
        "hidden": [
            "Poison Touch"
        ]
    },
    "base_hp": 6,
    "strength": "3/6",
    "dexterity": "2/4",
    "vitality": "2/5",
    "special": "2/4",
    "insight": "3/6",
    "moves": {
        "bronze": [
            "Disable",
            "Harden",
            "Mud-Slap",
            "Poison Gas",
            "Pound",
            "Venom Drench"
        ],
        "silver": [
            "Fling",
            "Minimize",
            "Mud Bomb",
            "Mud Shot",
            "Screech",
            "Sludge",
            "Sludge Bomb",
            "Sludge Wave",
            "Smog",
            "Toxic"
        ],
        "gold": [
            "Acid Armor",
            "Belch",
            "Gunk Shot",
            "Memento"
        ],
        "platinum": [],
        "diamond": [],
        "tm": [
            "Acid Armor",
            "Acid Spray",
            "Attract",
            "Belch",
            "Bide",
            "Body Slam",
            "Brick Break",
            "Captivate",
            "Confide",
            "Confuse Ray",
            "Curse",
            "Dark Pulse",
            "Dig",
            "Disable",
            "Double Team",
            "Drain Punch",
            "Dynamic Punch",
            "Endure",
            "Explosion",
            "Facade",
            "Fire Blast",
            "Fire Punch",
            "Flamethrower",
            "Fling",
            "Focus Blast",
            "Focus Punch",
            "Frustration",
            "Giga Drain",
            "Giga Impact",
            "Gunk Shot",
            "Harden",
            "Haze",
            "Helping Hand",
            "Hex",
            "Hidden Power",
            "Hyper Beam",
            "Ice Punch",
            "Imprison",
            "Incinerate",
            "Infestation",
            "Knock Off",
            "Lash Out",
            "Lunge",
            "Mega Drain",
            "Memento",
            "Metronome",
            "Mimic",
            "Minimize",
            "Mud Shot",
            "Mud-Slap",
            "Natural Gift",
            "Pain Split",
            "Payback",
            "Poison Gas",
            "Poison Jab",
            "Pound",
            "Power-Up Punch",
            "Protect",
            "Rage",
            "Rain Dance",
            "Rest",
            "Return",
            "Rock Slide",
            "Rock Smash",
            "Rock Tomb",
            "Round",
            "Sandstorm",
            "Scary Face",
            "Screech",
            "Secret Power",
            "Selfdestruct",
            "Shadow Ball",
            "Shock Wave",
            "Sleep Talk",
            "Sludge",
            "Sludge Bomb",
            "Sludge Wave",
            "Smog",
            "Snore",
            "Spite",
            "Strength",
            "Substitute",
            "Sunny Day",
            "Swagger",
            "Swift",
            "Take Down",
            "Taunt",
            "Tera Blast",
            "Thief",
            "Thunder",
            "Thunder Punch",
            "Thunderbolt",
            "Torment",
            "Toxic",
            "Toxic Spikes",
            "Venom Drench",
            "Venoshock",
            "Zap Cannon",
            "Zen Headbutt",
            "Agility",
            "Amnesia",
            "Headbutt",
            "Iron Defense",
            "Nasty Plot",
            "Splash",
            "Swords Dance"
        ],
        "tutor": [
            "Block",
            "Body Slam",
            "Dark Pulse",
            "Explosion",
            "Fire Punch",
            "Flamethrower",
            "Focus Punch",
            "Giga Drain",
            "Gunk Shot",
            "Harden",
            "Ice Punch",
            "Mimic",
            "Mud-Slap",
            "Pain Split",
            "Poison Gas",
            "Pound",
            "Shock Wave",
            "Sleep Talk",
            "Snore",
            "Substitute",
            "Thunder Punch",
            "Thunderbolt",
            "Venom Drench"
        ],
        "egg": [
            "Acid Spray",
            "Curse",
            "Explosion",
            "Haze",
            "Imprison",
            "Lick",
            "Mean Look",
            "Power-Up Punch",
            "Scary Face",
            "Shadow Punch",
            "Shadow Sneak",
            "Spit Up",
            "Stockpile",
            "Swallow"
        ],
        "level1_g3_7": [
            "Harden",
            "Poison Gas",
            "Pound",
            "Mud-Slap",
            "Venom Drench"
        ]
    }
}
