{
    "number": 20,
    "name": "Raticate",
    "types": [
        "Normal"
    ],
    "abilities": {
        "normal": [
            "Run Away",
            "Guts"
        ],
        "hidden": [
            "Hustle"
        ]
    },
    "base_hp": 4,
    "strength": "2/5",
    "dexterity": "3/6",
    "vitality": "2/4",
    "special": "2/4",
    "insight": "2/4",
    "moves": {
        "bronze": [
            "Bite",
            "Focus Energy",
            "Quick Attack",
            "Scary Face",
            "Swords Dance",
            "Tackle",
            "Tail Whip"
        ],
        "silver": [
            "Assurance",
            "Crunch",
            "Hyper Fang",
            "Laser Focus",
            "Pursuit",
            "Sucker Punch",
            "Take Down"
        ],
        "gold": [
            "Double-Edge",
            "Endeavor",
            "Super Fang"
        ],
        "platinum": [],
        "diamond": [],
        "tm": [
            "Assurance",
            "Attract",
            "Bide",
            "Bite",
            "Blizzard",
            "Body Slam",
            "Bubble Beam",
            "Captivate",
            "Charge Beam",
            "Confide",
            "Crunch",
            "Curse",
            "Cut",
            "Defense Curl",
            "Dig",
            "Double Team",
            "Double-Edge",
            "Endeavor",
            "Endure",
            "Facade",
            "Focus Energy",
            "Frustration",
            "Giga Impact",
            "Grass Knot",
            "Headbutt",
            "Hidden Power",
            "Hyper Beam",
            "Ice Beam",
            "Icy Wind",
            "Iron Tail",
            "Laser Focus",
            "Mimic",
            "Mud-Slap",
            "Natural Gift",
            "Pluck",
            "Protect",
            "Quick Attack",
            "Rage",
            "Rain Dance",
            "Rest",
            "Retaliate",
            "Return",
            "Roar",
            "Rock Smash",
            "Round",
            "Scary Face",
            "Secret Power",
            "Shadow Ball",
            "Shock Wave",
            "Skull Bash",
            "Sleep Talk",
            "Snore",
            "Strength",
            "Substitute",
            "Sucker Punch",
            "Sunny Day",
            "Super Fang",
            "Swagger",
            "Swift",
            "Swords Dance",
            "Tackle",
            "Tail Whip",
            "Take Down",
            "Taunt",
            "Thief",
            "Thunder",
            "Thunder Wave",
            "Thunderbolt",
            "Toxic",
            "U-turn",
            "Water Gun",
            "Wild Charge",
            "Work Up",
            "Agility",
            "Amnesia",
            "Helping Hand",
            "Iron Defense",
            "Metronome",
            "Nasty Plot",
            "Splash",
            "Tera Blast"
        ],
        "tutor": [
            "Body Slam",
            "Counter",
            "Covet",
            "Double-Edge",
            "Endeavor",
            "Focus Energy",
            "Ice Beam",
            "Icy Wind",
            "Iron Tail",
            "Last Resort",
            "Mimic",
            "Mud-Slap",
            "Quick Attack",
            "Scary Face",
            "Shock Wave",
            "Sleep Talk",
            "Snore",
            "Stomping Tantrum",
            "Substitute",
            "Sucker Punch",
            "Super Fang",
            "Swift",
            "Swords Dance",
            "Tackle",
            "Tail Whip",
            "Throat Chop",
            "Thunder Wave",
            "Thunderbolt",
            "Uproar",
            "Zen Headbutt"
        ],
        "egg": [
            "Bite",
            "Counter",
            "Final Gambit",
            "Flame Wheel",
            "Fury Swipes",
            "Last Resort",
            "Me First",
            "Revenge",
            "Reversal",
            "Screech",
            "Swagger",
            "Uproar"
        ],
        "level1_g3_7": [
            "Quick Attack",
            "Tackle",
            "Tail Whip",
            "Focus Energy",
            "Swords Dance",
            "Scary Face"
        ]
    }
}
