{
    "number": 287,
    "name": "Slakoth",
    "types": [
        "Normal"
    ],
    "abilities": {
        "normal": [
            "Truant"
        ],
        "hidden": []
    },
    "base_hp": 4,
    "strength": "2/4",
    "dexterity": "1/2",
    "vitality": "2/4",
    "special": "1/3",
    "insight": "1/3",
    "moves": {
        "bronze": [
            "Encore",
            "Scratch",
            "Slack Off",
            "Yawn"
        ],
        "silver": [
            "Amnesia",
            "Chip Away",
            "Counter",
            "Covet",
            "Feint Attack",
            "Flail",
            "Headbutt",
            "Rest",
            "Throat Chop"
        ],
        "gold": [
            "Play Rough"
        ],
        "platinum": [],
        "diamond": [],
        "tm": [
            "Aerial Ace",
            "Amnesia",
            "Attract",
            "Blizzard",
            "Body Slam",
            "Brick Break",
            "Bulk Up",
            "Captivate",
            "Chilling Water",
            "Confide",
            "Counter",
            "Covet",
            "Curse",
            "Cut",
            "Double Team",
            "Encore",
            "Endure",
            "Facade",
            "False Swipe",
            "Fire Blast",
            "Fire Punch",
            "Flail",
            "Flamethrower",
            "Fling",
            "Focus Punch",
            "Frustration",
            "Gunk Shot",
            "Headbutt",
            "Helping Hand",
            "Hidden Power",
            "Hone Claws",
            "Ice Beam",
            "Ice Punch",
            "Icy Wind",
            "Incinerate",
            "Metal Claw",
            "Metronome",
            "Mud Shot",
            "Mud-Slap",
            "Natural Gift",
            "Play Rough",
            "Poison Jab",
            "Power-Up Punch",
            "Protect",
            "Rain Dance",
            "Rest",
            "Retaliate",
            "Return",
            "Rock Slide",
            "Rock Smash",
            "Rock Tomb",
            "Round",
            "Scratch",
            "Secret Power",
            "Seed Bomb",
            "Shadow Ball",
            "Shadow Claw",
            "Shock Wave",
            "Slack Off",
            "Sleep Talk",
            "Solar Beam",
            "Strength",
            "Substitute",
            "Sunny Day",
            "Swagger",
            "Take Down",
            "Tera Blast",
            "Thief",
            "Throat Chop",
            "Thunder",
            "Thunder Punch",
            "Thunderbolt",
            "Toxic",
            "Water Pulse",
            "Work Up",
            "X-Scissor",
            "Yawn",
            "Zen Headbutt",
            "Agility",
            "Iron Defense",
            "Nasty Plot",
            "Snore",
            "Splash",
            "Swords Dance"
        ],
        "tutor": [
            "After You",
            "Body Slam",
            "Counter",
            "Covet",
            "Double-Edge",
            "Fire Punch",
            "Focus Punch",
            "Fury Cutter",
            "Gunk Shot",
            "Ice Punch",
            "Icy Wind",
            "Mega Kick",
            "Mega Punch",
            "Mimic",
            "Mud-Slap",
            "Rock Slide",
            "Scratch",
            "Seismic Toss",
            "Shock Wave",
            "Sleep Talk",
            "Snore",
            "Substitute",
            "Sucker Punch",
            "Thunder Punch",
            "Water Pulse",
            "Yawn"
        ],
        "egg": [
            "After You",
            "Body Slam",
            "Crush Claw",
            "Curse",
            "Hammer Arm",
            "Night Slash",
            "Pursuit",
            "Slash",
            "Sleep Talk",
            "Snore",
            "Tickle"
        ],
        "level1_g3_7": [
            "Scratch",
            "Yawn"
        ]
    }
}
