{
    "number": 234,
    "name": "Stantler",
    "types": [
        "Normal"
    ],
    "abilities": {
        "normal": [
            "Intimidate",
            "Frisk"
        ],
        "hidden": [
            "Sap Sipper"
        ]
    },
    "base_hp": 5,
    "strength": "3/6",
    "dexterity": "2/5",
    "vitality": "2/4",
    "special": "2/5",
    "insight": "2/4",
    "moves": {
        "bronze": [
            "Astonish",
            "Hypnosis",
            "Leer",
            "Tackle"
        ],
        "silver": [
            "Calm Mind",
            "Confuse Ray",
            "Role Play",
            "Sand Attack",
            "Stomp",
            "Take Down"
        ],
        "gold": [
            "Captivate",
            "Double-Edge",
            "Entrainment",
            "Imprison",
            "Jump Kick",
            "Lunge",
            "Me First",
            "Zen Headbutt"
        ],
        "platinum": [],
        "diamond": [],
        "tm": [
            "Agility",
            "Astonish",
            "Attract",
            "Body Slam",
            "Bulldoze",
            "Calm Mind",
            "Captivate",
            "Charge Beam",
            "Confide",
            "Confuse Ray",
            "Curse",
            "Detect",
            "Dig",
            "Double Team",
            "Double-Edge",
            "Dream Eater",
            "Earth Power",
            "Earthquake",
            "Endure",
            "Energy Ball",
            "Entrainment",
            "Facade",
            "Flash",
            "Frustration",
            "Future Sight",
            "Giga Impact",
            "Gravity",
            "Headbutt",
            "Helping Hand",
            "Hidden Power",
            "Hyper Beam",
            "Hypnosis",
            "Imprison",
            "Iron Tail",
            "Leer",
            "Light Screen",
            "Lunge",
            "Mud-Slap",
            "Natural Gift",
            "Nightmare",
            "Protect",
            "Psybeam",
            "Psych Up",
            "Psychic",
            "Psyshock",
            "Rain Dance",
            "Reflect",
            "Rest",
            "Retaliate",
            "Return",
            "Roar",
            "Role Play",
            "Round",
            "Sand Attack",
            "Scary Face",
            "Secret Power",
            "Shadow Ball",
            "Shock Wave",
            "Skill Swap",
            "Sleep Talk",
            "Snore",
            "Solar Beam",
            "Spite",
            "Stomp",
            "Stored Power",
            "Substitute",
            "Sunny Day",
            "Swagger",
            "Swift",
            "Tackle",
            "Take Down",
            "Tera Blast",
            "Thief",
            "Throat Chop",
            "Thunder",
            "Thunder Wave",
            "Thunderbolt",
            "Toxic",
            "Trailblaze",
            "Trick",
            "Trick Room",
            "Uproar",
            "Wild Charge",
            "Work Up",
            "Zen Headbutt",
            "Amnesia",
            "Iron Defense",
            "Metronome",
            "Nasty Plot",
            "Splash",
            "Swords Dance"
        ],
        "tutor": [
            "Body Slam",
            "Bounce",
            "Bulldoze",
            "Calm Mind",
            "Charge Beam",
            "Double-Edge",
            "Dream Eater",
            "Energy Ball",
            "Giga Impact",
            "Gravity",
            "Iron Tail",
            "Last Resort",
            "Magic Room",
            "Me First",
            "Megahorn",
            "Mimic",
            "Mud-Slap",
            "Psychic",
            "Rest",
            "Role Play",
            "Shadow Ball",
            "Shock Wave",
            "Signal Beam",
            "Skill Swap",
            "Sleep Talk",
            "Snore",
            "Spite",
            "Substitute",
            "Sucker Punch",
            "Swift",
            "Tackle",
            "Throat Chop",
            "Thunder Wave",
            "Thunderbolt",
            "Uproar",
            "Wild Charge",
            "Zen Headbutt"
        ],
        "egg": [
            "Bite",
            "Disable",
            "Double Kick",
            "Extrasensory",
            "Light Screen",
            "Me First",
            "Megahorn",
            "Mud Sport",
            "Psych Up",
            "Psyshield Bash",
            "Rage",
            "Reflect",
            "Spite",
            "Swagger",
            "Thrash",
            "Zen Headbutt"
        ],
        "level1_g3_7": [
            "Tackle",
            "Me First"
        ]
    }
}
