{
    "number": 637,
    "name": "Volcarona",
    "types": [
        "Bug",
        "Fire"
    ],
    "abilities": {
        "normal": [
            "Flame Body"
        ],
        "hidden": [
            "Swarm"
        ]
    },
    "base_hp": 5,
    "strength": "2/4",
    "dexterity": "3/6",
    "vitality": "2/5",
    "special": "4/8",
    "insight": "3/6",
    "moves": {
        "bronze": [
            "Absorb",
            "Double-Edge",
            "Ember",
            "Fiery Dance",
            "Fire Spin",
            "Flame Charge",
            "Flare Blitz",
            "Gust",
            "Leech Life",
            "Quiver Dance",
            "String Shot",
            "Struggle Bug",
            "Take Down",
            "Whirlwind"
        ],
        "silver": [
            "Bug Bite",
            "Flame Wheel",
            "Screech"
        ],
        "gold": [
            "Amnesia",
            "Bug Buzz",
            "Fire Blast",
            "Heat Wave",
            "Hurricane",
            "Rage Powder",
            "Silver Wind"
        ],
        "platinum": [],
        "diamond": [],
        "tm": [
            "Acrobatics",
            "Aerial Ace",
            "Air Cutter",
            "Air Slash",
            "Amnesia",
            "Attract",
            "Body Slam",
            "Bug Bite",
            "Bug Buzz",
            "Calm Mind",
            "Confide",
            "Double Team",
            "Double-Edge",
            "Dual Wingbeat",
            "Endure",
            "Facade",
            "Fire Blast",
            "Fire Spin",
            "Flame Charge",
            "Flamethrower",
            "Flare Blitz",
            "Fly",
            "Frustration",
            "Giga Drain",
            "Giga Impact",
            "Heat Wave",
            "Hidden Power",
            "Hurricane",
            "Hyper Beam",
            "Incinerate",
            "Leech Life",
            "Light Screen",
            "Lunge",
            "Mystical Fire",
            "Overheat",
            "Poison Jab",
            "Pounce",
            "Protect",
            "Psychic",
            "Rain Dance",
            "Rest",
            "Return",
            "Roost",
            "Round",
            "Safeguard",
            "Screech",
            "Skitter Smack",
            "Sleep Talk",
            "Snore",
            "Solar Beam",
            "Struggle Bug",
            "Substitute",
            "Sunny Day",
            "Swagger",
            "Tailwind",
            "Take Down",
            "Tera Blast",
            "Toxic",
            "Trailblaze",
            "U-turn",
            "Wild Charge",
            "Will-O-Wisp",
            "Zen Headbutt",
            "Agility",
            "Curse",
            "Headbutt",
            "Helping Hand",
            "Iron Defense",
            "Metronome",
            "Nasty Plot",
            "Secret Power",
            "Splash",
            "Swords Dance"
        ],
        "tutor": [
            "Absorb",
            "Amnesia",
            "Bug Bite",
            "Bug Buzz",
            "Defog",
            "Dual Wingbeat",
            "Ember",
            "Fiery Dance",
            "Flame Wheel",
            "Flare Blitz",
            "Giga Drain",
            "Gust",
            "Heat Wave",
            "Hurricane",
            "Leech Life",
            "Magnet Rise",
            "Quiver Dance",
            "Rage Powder",
            "Roost",
            "Signal Beam",
            "Skitter Smack",
            "Sleep Talk",
            "Snore",
            "String Shot",
            "Tailwind",
            "Thrash",
            "Zen Headbutt"
        ],
        "egg": [
            "Absorb",
            "Endure",
            "Foresight",
            "Harden",
            "Magnet Rise",
            "Morning Sun",
            "String Shot",
            "Thrash",
            "Zen Headbutt"
        ],
        "level1_g3_7": [
            "Ember",
            "Gust",
            "Leech Life",
            "String Shot",
            "Amnesia",
            "Bug Buzz",
            "Fiery Dance",
            "Flame Wheel",
            "Flare Blitz",
            "Heat Wave",
            "Hurricane",
            "Quiver Dance",
            "Rage Powder",
            "Thrash",
            "Absorb"
        ]
    }
}
